optionsconfig/__init__.py
optionsconfig/argument_writer.py
optionsconfig/options.py
optionsconfig/schema.py
optionsconfig/builders/__init__.py
optionsconfig/builders/build_all.py
optionsconfig/builders/env_builder.py
optionsconfig/builders/readme_builder.py
optionsconfig-0.4.0.dist-info/licenses/LICENSE
optionsconfig-0.4.0.dist-info/METADATA
optionsconfig-0.4.0.dist-info/WHEEL
optionsconfig-0.4.0.dist-info/top_level.txt
optionsconfig-0.4.0.dist-info/RECORD
