Metadata-Version: 2.4
Name: optionsconfig
Version: 0.4.0
Summary: Unified configuration management for environment variables, CLI arguments, and documentation
License: MIT
Project-URL: Homepage, https://github.com/Surxe/OptionsConfig
Project-URL: Repository, https://github.com/Surxe/OptionsConfig
Requires-Python: >=3.8
License-File: LICENSE
Requires-Dist: python-dotenv>=0.19.0
Requires-Dist: loguru>=0.6.0
Provides-Extra: dev
Requires-Dist: pytest>=7.0; extra == "dev"
Requires-Dist: black>=22.0; extra == "dev"
Requires-Dist: mypy>=0.950; extra == "dev"
Provides-Extra: toml
Requires-Dist: tomli>=2.0.0; python_version < "3.11" and extra == "toml"
Dynamic: license-file
